dailygammonpy/__init__.py
dailygammonpy/connect.py
dailygammonpy/fileio.py
dailygammonpy-0.0.2.dist-info/LICENSE
dailygammonpy-0.0.2.dist-info/METADATA
dailygammonpy-0.0.2.dist-info/WHEEL
dailygammonpy-0.0.2.dist-info/top_level.txt
dailygammonpy-0.0.2.dist-info/RECORD
