Metadata-Version: 2.1
Name: dailygammonpy
Version: 0.0.2
Summary: Python package for DailyGammon
Author-email: Gergely Elias <gergely.elias@gmail.com>
License: The MIT License (MIT)        
Project-URL: Homepage, https://github.com/gergely-elias/dailygammonpy
Project-URL: Bug Tracker, https://github.com/gergely-elias/dailygammonpy/issues
Classifier: Programming Language :: Python :: 3
Classifier: License :: OSI Approved :: MIT License
Classifier: Operating System :: OS Independent
Requires-Python: >=3.7
License-File: LICENSE
